grag/__about__.py
grag/__init__.py
grag/components/__init__.py
grag/components/create_config.py
grag/components/embedding.py
grag/components/llm.py
grag/components/multivec_retriever.py
grag/components/parse_pdf.py
grag/components/prompt.py
grag/components/text_splitter.py
grag/components/utils.py
grag/components/vectordb/__init__.py
grag/components/vectordb/base.py
grag/components/vectordb/chroma_client.py
grag/components/vectordb/deeplake_client.py
grag/prompts/Llama-2_QA-refine_1.json
grag/prompts/Llama-2_QA_1.json
grag/prompts/Mixtral_QA_1.json
grag/prompts/__init__.py
grag/prompts/matcher.json
grag/quantize/__init__.py
grag/quantize/quantize.py
grag/quantize/utils.py
grag/rag/__init__.py
grag/rag/basic_rag.py
grag/resources/__init__.py
grag/resources/default_config.ini
grag-0.0.1.dist-info/METADATA
grag-0.0.1.dist-info/WHEEL
grag-0.0.1.dist-info/licenses/LICENSE
grag-0.0.1.dist-info/RECORD
