Metadata-Version: 2.3
Name: grag
Version: 0.0.1
Summary: A simple package for implementing RAG
Project-URL: Documentation, https://g-rag.org/
Project-URL: Issues, https://github.com/arjbingly/grag/issues
Project-URL: Repository, https://github.com/arjbingly/grag.git
Author-email: Arjun Bingly <arjunbin@gmail.com>, Sanchit Vijay <sanchitvj1026@gmail.com>
License:                     GNU AFFERO GENERAL PUBLIC LICENSE
License-File: LICENSE
Keywords: LLM,RAG,Retrieval Augmented Generation,quantization,retrieval
Classifier: Development Status :: 4 - Beta
Classifier: Environment :: GPU :: NVIDIA CUDA :: 12
Classifier: Programming Language :: Python
Classifier: Programming Language :: Python :: 3.10
Classifier: Programming Language :: Python :: 3.11
Classifier: Programming Language :: Python :: 3.12
Classifier: Programming Language :: Python :: Implementation :: CPython
Classifier: Programming Language :: Python :: Implementation :: PyPy
Classifier: Topic :: Scientific/Engineering :: Artificial Intelligence
Requires-Python: >=3.10
Requires-Dist: accelerate>=0.28.0
Requires-Dist: bitsandbytes>=0.42.0
Requires-Dist: chromadb>=0.4.13
Requires-Dist: deeplake>=3.8.27
Requires-Dist: huggingface-hub>=0.20.2
Requires-Dist: instructorembedding>=1.0.1
Requires-Dist: langchain>=0.1.5
Requires-Dist: llama-cpp-python>=0.2.43
Requires-Dist: pdfplumber>=0.10.3
Requires-Dist: poppler-utils>=0.1.0
Requires-Dist: pydantic>=2.5.0
Requires-Dist: rouge-score>=0.1.2
Requires-Dist: sentence-transformers==2.2.2
Requires-Dist: streamlit>=1.31.1
Requires-Dist: tesseract>=0.1.3
Requires-Dist: torch>=2.2.0
Requires-Dist: tqdm>=4.65.0
Requires-Dist: transformers>=4.37.1
Requires-Dist: unstructured[pdf]>=0.12.3
Provides-Extra: dev
Requires-Dist: mypy; extra == 'dev'
Requires-Dist: pydata-sphinx-theme; extra == 'dev'
Requires-Dist: pytest; extra == 'dev'
Requires-Dist: pytest-cov; extra == 'dev'
Requires-Dist: ruff; extra == 'dev'
Requires-Dist: sphinx; extra == 'dev'
Requires-Dist: sphinx-gallery; extra == 'dev'
